CFS/__init__.py
CFS/iter_int.py
CFS/iter_lie.py
CFS/pol_inputs.py
CFS/single_iter_int.py
CFS/single_iter_lie.py
CFS/sym_CFS.py
cfspy-1.2.3.dist-info/licenses/LICENSE
cfspy-1.2.3.dist-info/METADATA
cfspy-1.2.3.dist-info/WHEEL
cfspy-1.2.3.dist-info/top_level.txt
cfspy-1.2.3.dist-info/RECORD
