Metadata-Version: 2.4
Name: CFSpy
Version: 1.2.3
Summary: Chen-Fliess series computation
Home-page: https://github.com/iperezav/CFSpy/
Author: Ivan Perez Avellaneda
Author-email: <iperezave@gmail.com>
License: MIT
Keywords: Chen-Fliess series,nonlinear system,input-output system,ODEs,control system,system theory,python
Classifier: Development Status :: 5 - Production/Stable
Classifier: Intended Audience :: Science/Research
Classifier: Programming Language :: Python :: 3
Classifier: Operating System :: Unix
Classifier: Operating System :: MacOS :: MacOS X
Classifier: Operating System :: Microsoft :: Windows
License-File: LICENSE
Requires-Dist: numpy
Requires-Dist: sympy
Dynamic: author
Dynamic: author-email
Dynamic: classifier
Dynamic: description
Dynamic: description-content-type
Dynamic: home-page
Dynamic: keywords
Dynamic: license
Dynamic: license-file
Dynamic: requires-dist
Dynamic: summary
